bluesky_widgets/__init__.py
bluesky_widgets/_matplotlib_axes.py
bluesky_widgets/_version.py
bluesky_widgets/conftest.py
bluesky_widgets/apps/__init__.py
bluesky_widgets/apps/queue_monitor/__init__.py
bluesky_widgets/apps/queue_monitor/main.py
bluesky_widgets/apps/queue_monitor/settings.py
bluesky_widgets/apps/queue_monitor/viewer.py
bluesky_widgets/apps/queue_monitor/widgets.py
bluesky_widgets/examples/__init__.py
bluesky_widgets/examples/headless_figures.py
bluesky_widgets/examples/ipy_qt_figure.py
bluesky_widgets/examples/ipy_qt_figures.py
bluesky_widgets/examples/ipy_qt_images.py
bluesky_widgets/examples/ipy_qt_rastered_image.py
bluesky_widgets/examples/jupyter_viewer.py
bluesky_widgets/examples/kafka_figures.py
bluesky_widgets/examples/napari_dock_widgets.py
bluesky_widgets/examples/pyFAI_dialog.py
bluesky_widgets/examples/qt_app_integration.py
bluesky_widgets/examples/qt_app_search_integration.py
bluesky_widgets/examples/qt_run_tree_view.py
bluesky_widgets/examples/qt_search.py
bluesky_widgets/examples/advanced/__init__.py
bluesky_widgets/examples/advanced/qt_viewer_with_search.py
bluesky_widgets/examples/advanced/qt_with_RE_worker.py
bluesky_widgets/examples/utils/__init__.py
bluesky_widgets/examples/utils/add_search_mixin.py
bluesky_widgets/examples/utils/generate_mongo_data.py
bluesky_widgets/examples/utils/generate_msgpack_data.py
bluesky_widgets/examples/utils/get_run_images.py
bluesky_widgets/examples/utils/stream_data_kafka.py
bluesky_widgets/examples/utils/stream_data_zmq.py
bluesky_widgets/headless/__init__.py
bluesky_widgets/headless/figures.py
bluesky_widgets/headless/_tests/__init__.py
bluesky_widgets/headless/_tests/test_closing.py
bluesky_widgets/jupyter/__init__.py
bluesky_widgets/jupyter/_search_input.py
bluesky_widgets/jupyter/figures.py
bluesky_widgets/jupyter/zmq_dispatcher.py
bluesky_widgets/models/__init__.py
bluesky_widgets/models/_heuristics.py
bluesky_widgets/models/plot_builders.py
bluesky_widgets/models/plot_specs.py
bluesky_widgets-0.0.17.dist-info/licenses/AUTHORS.rst
bluesky_widgets-0.0.17.dist-info/licenses/LICENSE
bluesky_widgets-0.0.17.dist-info/METADATA
bluesky_widgets-0.0.17.dist-info/WHEEL
bluesky_widgets-0.0.17.dist-info/entry_points.txt
bluesky_widgets-0.0.17.dist-info/top_level.txt
bluesky_widgets-0.0.17.dist-info/RECORD
