Metadata-Version: 2.4
Name: bluesky-widgets
Version: 0.0.17
Summary: Toolbox of widgets for visualizing streaming data
Home-page: https://github.com/bluesky/bluesky-widgets
Author: Brookhaven National Lab
Author-email: dallan@bnl.gov
License: BSD (3-clause)
Classifier: Development Status :: 2 - Pre-Alpha
Classifier: Natural Language :: English
Classifier: Programming Language :: Python :: 3
Requires-Python: >=3.6
License-File: LICENSE
License-File: AUTHORS.rst
Requires-Dist: bluesky-live>=0.0.7
Requires-Dist: numpy
Requires-Dist: suitcase-utils<=0.5.3
Provides-Extra: examples
Requires-Dist: bluesky; extra == "examples"
Requires-Dist: databroker; extra == "examples"
Requires-Dist: ophyd>=1.5.3; extra == "examples"
Requires-Dist: pyzmq; extra == "examples"
Requires-Dist: suitcase-msgpack; extra == "examples"
Provides-Extra: jupyter
Requires-Dist: ipywidgets; extra == "jupyter"
Requires-Dist: ipympl; extra == "jupyter"
Requires-Dist: matplotlib; extra == "jupyter"
Provides-Extra: pyside2
Requires-Dist: PySide2; extra == "pyside2"
Requires-Dist: qtpy; extra == "pyside2"
Requires-Dist: matplotlib; extra == "pyside2"
Provides-Extra: pyqt5
Requires-Dist: PyQt5; extra == "pyqt5"
Requires-Dist: qtpy; extra == "pyqt5"
Requires-Dist: matplotlib; extra == "pyqt5"
Provides-Extra: complete
Requires-Dist: PyQt5; extra == "complete"
Requires-Dist: PySide2; extra == "complete"
Requires-Dist: bluesky; extra == "complete"
Requires-Dist: databroker; extra == "complete"
Requires-Dist: ipympl; extra == "complete"
Requires-Dist: ipywidgets; extra == "complete"
Requires-Dist: matplotlib; extra == "complete"
Requires-Dist: ophyd>=1.5.3; extra == "complete"
Requires-Dist: pyzmq; extra == "complete"
Requires-Dist: qtpy; extra == "complete"
Requires-Dist: suitcase-msgpack; extra == "complete"
Dynamic: author
Dynamic: author-email
Dynamic: classifier
Dynamic: description
Dynamic: home-page
Dynamic: license
Dynamic: license-file
Dynamic: provides-extra
Dynamic: requires-dist
Dynamic: requires-python
Dynamic: summary
